lmeval/__init__.py
lmeval/benchmark.py
lmeval/benchmark_test.py
lmeval/callback.py
lmeval/config.py
lmeval/custom_model.py
lmeval/end_to_end_test.py
lmeval/enums.py
lmeval/enums_test.py
lmeval/evaluator.py
lmeval/fixtures.py
lmeval/fixtures_test.py
lmeval/logger.py
lmeval/media.py
lmeval/question.py
lmeval/system_config.py
lmeval/task.py
lmeval/template_engine.py
lmeval/template_engine_test.py
lmeval/utils.py
lmeval/archive/__init__.py
lmeval/archive/archive.py
lmeval/archive/crypto.py
lmeval/archive/crypto_test.py
lmeval/archive/sqlite_archive.py
lmeval/archive/sqlite_archive_test.py
lmeval/cli/data.py
lmeval/cli/evalboard.py
lmeval/cli/ui_headtohead.py
lmeval/cli/ui_singlemodel.py
lmeval/cli/utils.py
lmeval/models/__init__.py
lmeval/models/gemini.py
lmeval/models/gemini_test.py
lmeval/models/httpmodel.py
lmeval/models/httpmodel_test.py
lmeval/models/litellm.py
lmeval/models/lmmodel.py
lmeval/models/lmmodel_test.py
lmeval/models/mock_model.py
lmeval/models/ollama.py
lmeval/models/ollama_test.py
lmeval/models/openai.py
lmeval/models/openai_test.py
lmeval/models/tests_utils.py
lmeval/models/vertex.py
lmeval/models/vertex_test.py
lmeval/prompts/__init__.py
lmeval/prompts/adversarial_prompts.py
lmeval/prompts/boolean_prompts.py
lmeval/prompts/boolean_prompts_test.py
lmeval/prompts/multi_choices_prompts.py
lmeval/prompts/multi_choices_prompts_test.py
lmeval/prompts/prompt.py
lmeval/prompts/prompt_tests.py
lmeval/prompts/text_generation_prompts.py
lmeval/prompts/text_generation_prompts_test.py
lmeval/regression_testing/__init__.py
lmeval/regression_testing/fixtures.py
lmeval/regression_testing/test_end_to_end.py
lmeval/regression_testing/test_evaluator.py
lmeval/regression_testing/test_fixtures.py
lmeval/scorers/__init__.py
lmeval/scorers/boolean_answer.py
lmeval/scorers/boolean_test.py
lmeval/scorers/contain_text.py
lmeval/scorers/containt_text_test.py
lmeval/scorers/dummy_scorer.py
lmeval/scorers/dummy_test.py
lmeval/scorers/exact_text.py
lmeval_framework-0.11.4.dist-info/LICENSE
lmeval_framework-0.11.4.dist-info/METADATA
lmeval_framework-0.11.4.dist-info/WHEEL
lmeval_framework-0.11.4.dist-info/entry_points.txt
lmeval_framework-0.11.4.dist-info/top_level.txt
lmeval_framework-0.11.4.dist-info/RECORD
