Metadata-Version: 2.2
Name: lmeval-framework
Version: 0.11.4
Summary: LMEval: Large Model Evaluation Framework
Requires-Python: >=3.10
License-File: LICENSE
Requires-Dist: pydantic>=2.10.6
Requires-Dist: dash>=2.18.2
Requires-Dist: dash-bootstrap-components>=1.7.1
Requires-Dist: immutabledict>=4.2.0
Requires-Dist: ipykernel>=6.29.5
Requires-Dist: litellm>1.61.16
Requires-Dist: matplotlib>=3.9.2
Requires-Dist: nbformat>=5.10.4
Requires-Dist: openai>=1.64.0
Requires-Dist: pandas>=2.2.3
Requires-Dist: tabulate>=0.9.0
Requires-Dist: tink>=1.10.0
Requires-Dist: typer>=0.15.1
Provides-Extra: vertex
Requires-Dist: google-cloud-aiplatform>=1.67.1; extra == "vertex"
